COPYRIGHTS.txt
LICENSE.txt
MANIFEST.in
README.rst
setup.py
CausalInference.egg-info/PKG-INFO
CausalInference.egg-info/SOURCES.txt
CausalInference.egg-info/dependency_links.txt
CausalInference.egg-info/top_level.txt
Causalinference.egg-info/SOURCES.txt
causalinference/__init__.py
causalinference/causal.py
causalinference/core/__init__.py
causalinference/core/data.py
causalinference/core/propensity.py
causalinference/core/strata.py
causalinference/core/summary.py
causalinference/estimators/__init__.py
causalinference/estimators/base.py
causalinference/estimators/blocking.py
causalinference/estimators/matching.py
causalinference/estimators/ols.py
causalinference/estimators/weighting.py
causalinference/utils/__init__.py
causalinference/utils/lalonde_data.txt
causalinference/utils/tools.py
causalinference/utils/vignette_data.txt
docs/conf.py
tests/test_blocking.py
tests/test_causal.py
tests/test_data.py
tests/test_matching.py
tests/test_ols.py
tests/test_propensity.py
tests/test_propensityselect.py
tests/test_summary.py
tests/test_tools.py
tests/test_weighting.py
tests/utils.py