Metadata-Version: 1.0
Name: CausalInference
Version: 0.1.1
Summary: Causal Inference in Python
Home-page: https://github.com/laurencium/causalinference
Author: Laurence Wong
Author-email: laurencium@gmail.com
License: LICENSE.txt
Platform: UNKNOWN
